{
    "fluentMethods": true,
    "relationships": [
        {
            "relationshipName": "competitionseason",
            "otherEntityName": "season",
            "relationshipType": "many-to-one",
            "relationshipValidateRules": [
                "required"
            ],
            "otherEntityField": "id"
        }
    ],
    "fields": [
        {
            "fieldName": "name",
            "fieldType": "String",
            "fieldValidateRules": [
                "required"
            ]
        }
    ],
    "changelogDate": "20170710162834",
    "dto": "no",
    "service": "no",
    "entityTableName": "competition",
    "pagination": "pager"
}
