{
    "fluentMethods": true,
    "relationships": [
        {
            "relationshipName": "matchcompetition",
            "otherEntityName": "competition",
            "relationshipType": "many-to-one",
            "relationshipValidateRules": [
                "required"
            ],
            "otherEntityField": "id"
        }
    ],
    "fields": [
        {
            "fieldName": "hometeam",
            "fieldType": "String",
            "fieldValidateRules": [
                "required"
            ]
        },
        {
            "fieldName": "awayteam",
            "fieldType": "String",
            "fieldValidateRules": [
                "required"
            ]
        },
        {
            "fieldName": "homegoals",
            "fieldType": "Integer"
        },
        {
            "fieldName": "awaygoals",
            "fieldType": "Integer"
        },
        {
            "fieldName": "location",
            "fieldType": "String",
            "fieldValidateRules": [
                "required"
            ]
        },
        {
            "fieldName": "description",
            "fieldType": "String",
            "fieldValidateRules": [
                "required"
            ]
        },
        {
            "fieldName": "matchdatetime",
            "fieldType": "ZonedDateTime",
            "fieldValidateRules": [
                "required"
            ]
        }
    ],
    "changelogDate": "20170710164239",
    "dto": "no",
    "service": "no",
    "entityTableName": "jhi_match",
    "pagination": "pager"
}
